tiddlywiki/LICENSE.txt
tiddlywiki/README.md
tiddlywiki/__init__.py
tiddlywiki/defaultworkspacelist.html
tiddlywiki/pyproject.toml
tiddlywiki/setup.cfg
tiddlywiki/setup.py
tiddlywiki/twpye.py
tiddlywiki/twpym.py
tiddlywiki/twpyu.py
tiddlywiki/tiddlywiki.egg-info/PKG-INFO
tiddlywiki/tiddlywiki.egg-info/SOURCES.txt
tiddlywiki/tiddlywiki.egg-info/dependency_links.txt
tiddlywiki/tiddlywiki.egg-info/entry_points.txt
tiddlywiki/tiddlywiki.egg-info/requires.txt
tiddlywiki/tiddlywiki.egg-info/top_level.txt
tiddlywiki-0.0.6.dist-info/LICENSE.txt
tiddlywiki-0.0.6.dist-info/METADATA
tiddlywiki-0.0.6.dist-info/WHEEL
tiddlywiki-0.0.6.dist-info/entry_points.txt
tiddlywiki-0.0.6.dist-info/top_level.txt
tiddlywiki-0.0.6.dist-info/RECORD
