Metadata-Version: 2.1
Name: tiddlywiki
Version: 0.0.6
Summary: A full featured desktop client for editing and managing TiddlyWiki html files - simple, powerful, elegant and efficient.
Home-page: https://twpy.org
Author: The TWPY Organization
Author-email: thecoolestguyinthecosmos@gmail.com
Project-URL: Bug Tracker, https://twpy.org/bugs
Classifier: Programming Language :: Python :: 3
Classifier: License :: OSI Approved :: BSD License
Classifier: Operating System :: OS Independent
Requires-Python: >=3.6
License-File: LICENSE.txt
Requires-Dist: pywebview
